dbt/adapters/impala/.env
dbt/adapters/impala/__init__.py
dbt/adapters/impala/__version__.py
dbt/adapters/impala/cloudera_tracking.py
dbt/adapters/impala/column.py
dbt/adapters/impala/connections.py
dbt/adapters/impala/impl.py
dbt/adapters/impala/relation.py
dbt/include/impala/__init__.py
dbt/include/impala/dbt_project.yml
dbt/include/impala/sample_profiles.yml
dbt/include/impala/macros/adapters.sql
dbt/include/impala/macros/apply_grants.sql
dbt/include/impala/macros/catalog.sql
dbt/include/impala/macros/incremental.sql
dbt/include/impala/macros/insertoverwrite.sql
dbt/include/impala/macros/seed.sql
dbt/include/impala/macros/utils/any_value.sql
dbt/include/impala/macros/utils/array_append.sql
dbt/include/impala/macros/utils/array_concat.sql
dbt/include/impala/macros/utils/array_construct.sql
dbt/include/impala/macros/utils/bool_or.sql
dbt/include/impala/macros/utils/concat.sql
dbt/include/impala/macros/utils/dateadd.sql
dbt/include/impala/macros/utils/datediff.sql
dbt/include/impala/macros/utils/escape_single_quotes.sql
dbt/include/impala/macros/utils/hash.sql
dbt/include/impala/macros/utils/last_day.sql
dbt/include/impala/macros/utils/listagg.sql
dbt/include/impala/macros/utils/position.sql
dbt/include/impala/macros/utils/split_part.sql
dbt/include/impala/macros/utils/timestamps.sql
dbt_impala-1.9.0.data/data/.env
dbt_impala-1.9.0.dist-info/LICENSE
dbt_impala-1.9.0.dist-info/METADATA
dbt_impala-1.9.0.dist-info/WHEEL
dbt_impala-1.9.0.dist-info/top_level.txt
dbt_impala-1.9.0.dist-info/RECORD
