Metadata-Version: 2.1
Name: dbt-impala
Version: 1.9.0
Summary: Impala adapter for DBT
Home-page: https://github.com/cloudera/dbt-impala
Author: Cloudera
Author-email: innovation-feedback@cloudera.com
Classifier: Development Status :: 4 - Beta
Classifier: Operating System :: MacOS :: MacOS X
Classifier: Operating System :: Microsoft :: Windows
Classifier: Operating System :: POSIX :: Linux
Classifier: Programming Language :: Python :: 3.7
Classifier: Programming Language :: Python :: 3.8
Classifier: Programming Language :: Python :: 3.9
Classifier: License :: OSI Approved :: Apache Software License
License-File: LICENSE
Requires-Dist: dbt-core (~=1.9.0)
Requires-Dist: impyla (==0.18)
Requires-Dist: python-decouple (>=3.6)
